wordle_helper/__init__.py
wordle_helper/cli.py
python_wordle_helper-1.0.1.dist-info/LICENSE
python_wordle_helper-1.0.1.dist-info/METADATA
python_wordle_helper-1.0.1.dist-info/WHEEL
python_wordle_helper-1.0.1.dist-info/entry_points.txt
python_wordle_helper-1.0.1.dist-info/RECORD
