Metadata-Version: 2.1
Name: python-wordle-helper
Version: 1.0.1
Summary: Cheat at Wordle!
Home-page: https://gitlab.com/henxing/wordle_helper
License: Unlicense
Keywords: wordle
Author: Hugh Enxing
Author-email: henxing@gmail.com
Maintainer: Hugh Enxing
Maintainer-email: henxing@gmail.com
Requires-Python: >=3.9,<4.0
Classifier: License :: OSI Approved
Classifier: Programming Language :: Python :: 3
Classifier: Programming Language :: Python :: 3.9
Classifier: Programming Language :: Python :: 3.10
Classifier: Programming Language :: Python :: 3.11
Requires-Dist: numpy (>=1.23.0,<2.0.0)
Requires-Dist: requests (>=2.28.1,<3.0.0)
Requires-Dist: wordfreq (>=3.0.1,<4.0.0)
Project-URL: Repository, https://gitlab.com/henxing/wordle_helper
